[
  { "label": "কোন পোশাক নেই", "quantity": "0", "name": "পোশাক" },
  { "label": "১টি পোশাক", "quantity": "1", "name": "পোশাক" },
  { "label": "২টি পোশাক", "quantity": "2", "name": "পোশাক" },
  { "label": "৩টি পোশাক", "quantity": "3", "name": "পোশাক" },
  { "label": "৪টি পোশাক", "quantity": "4", "name": "পোশাক" },
  { "label": "৫টি পোশাক", "quantity": "5", "name": "পোশাক" },
  { "label": "৬টি পোশাক", "quantity": "6", "name": "পোশাক" },
  { "label": "৭টি পোশাক", "quantity": "7", "name": "পোশাক" },
  { "label": "৮টি পোশাক", "quantity": "8", "name": "পোশাক" },
  { "label": "৯টি পোশাক", "quantity": "9", "name": "পোশাক" },
  { "label": "১০টি পোশাক", "quantity": "10", "name": "পোশাক" }
]